README
setup.cfg
setup.py
rijndael/__init__.py
rijndael.egg-info/PKG-INFO
rijndael.egg-info/SOURCES.txt
rijndael.egg-info/dependency_links.txt
rijndael.egg-info/top_level.txt
rijndael/cipher/__init__.py
rijndael/cipher/blockcipher.py
rijndael/cipher/crypt.py
rijndael/cipher/method.py
rijndael/tests/__init__.py
rijndael/tests/sanity_tests.py
rijndael/utils/__init__.py
rijndael/utils/cvt.py
rijndael/utils/padding.py