Metadata-Version: 1.1
Name: rijndael
Version: 0.1.1
Summary: Rijndael AES encryption algorithm in pure python.
Home-page: https://github.com/moeenz/rijndael
Author: Moeen Zamani
Author-email: moeen.zamani@gmail.com
License: MIT
Platform: UNKNOWN
Classifier: Environment :: Console
Classifier: Operating System :: Microsoft :: Windows
Classifier: Operating System :: Unix
Classifier: Programming Language :: Python
